[
  {
    "key":583474648,"datasetKey":"4f29b6ab-20c0-4479-8795-4915bedcebd1","publishingOrgKey":"66522820-055c-11d8-b84e-b8a03c50a862","networkKeys":["99d66b6c-9087-452f-a9d4-f15f2c2d0e7e"],"installationKey":"a43950ae-eb88-4ef4-bfff-43bcf12885ad","hostingOrganizationKey":"66522820-055c-11d8-b84e-b8a03c50a862","publishingCountry":"US","protocol":"EML","lastCrawled":"2024-08-05T22:57:09.849+00:00","lastParsed":"2024-08-05T22:58:07.667+00:00","crawlId":671,"extensions":{},"basisOfRecord":"PRESERVED_SPECIMEN","occurrenceStatus":"PRESENT","sex":"MALE","taxonKey":6176241,"kingdomKey":1,"phylumKey":44,"classKey":212,"orderKey":1450,"familyKey":9348,"genusKey":8373955,"speciesKey":2497295,"acceptedTaxonKey":6176241,"scientificName":"Asio flammeus galapagoensis (Gould, 1837)","acceptedScientificName":"Asio flammeus galapagoensis (Gould, 1837)","kingdom":"Animalia","phylum":"Chordata","order":"Strigiformes","family":"Strigidae","genus":"Asio","species":"Asio flammeus","genericName":"Asio","specificEpithet":"flammeus","infraspecificEpithet":"galapagoensis","taxonRank":"SUBSPECIES","taxonomicStatus":"ACCEPTED","continent":"SOUTH_AMERICA","stateProvince":"Galapagos Islands","gadm":{},"higherGeography":"South America, Ecuador, Galapagos Islands, Isabela Island","year":1906,"month":8,"day":10,"eventDate":"1906-08-10","startDayOfYear":222,"endDayOfYear":222,"issues":[],"modified":"2024-03-27T11:55:18.000+00:00","lastInterpreted":"2024-08-05T22:58:07.667+00:00","license":"http://creativecommons.org/publicdomain/zero/1.0/legalcode","isSequenced":false,"identifiers":[{"identifier":"urn:catalog:CAS:ORN:2920"}],"media":[],"facts":[],"relations":[],"institutionKey":"d2a27206-87ab-47ea-b5fc-d2e57054b688","collectionKey":"9525d06a-2187-4c50-b34e-2783b8bdff8c","isInCluster":false,"recordedBy":"J. S. Hunter","preparations":"Feather; Skin Study; toepad","class":"Aves","countryCode":"EC","recordedByIDs":[],"identifiedByIDs":[],"gbifRegion":"LATIN_AMERICA","country":"Ecuador","publishedByGbifRegion":"NORTH_AMERICA","identifier":"urn:catalog:CAS:ORN:2920","institutionID":"http://grscicoll.org/institution/california-academy-sciences","nomenclaturalCode":"ICZN","verbatimEventDate":"10 August 1906","locality":"Isabela Island; Cowley Bay","county":"Isabela Island","language":"en","collectionCode":"ORN","gbifID":"583474648","occurrenceID":"urn:catalog:CAS:ORN:2920","type":"Physical Object","catalogNumber":"2920","institutionCode":"CAS","higherClassification":"Aves,Strigiformes,Strigidae","collectionID":"https://www.gbif.org/grscicoll/collection/9525d06a-2187-4c50-b34e-2783b8bdff8c"
  }
]